puc16/__init__.py
puc16/asm.py
puc16/assembler.py
puc16/cc.py
puc16/compiler.py
puc16/disassembler.py
puc16/emitter.py
puc16/instructions.py
puc16/simulator.py
puc16/ppci/__init__.py
puc16/ppci/api.py
puc16/ppci/cil.py
puc16/ppci/common.py
puc16/ppci/ir.py
puc16/ppci/runtime.py
puc16/ppci/arch/__init__.py
puc16/ppci/arch/arch.py
puc16/ppci/arch/arch_info.py
puc16/ppci/arch/asm_printer.py
puc16/ppci/arch/cc.py
puc16/ppci/arch/data_instructions.py
puc16/ppci/arch/effects.py
puc16/ppci/arch/encoding.py
puc16/ppci/arch/example.py
puc16/ppci/arch/generic_instructions.py
puc16/ppci/arch/isa.py
puc16/ppci/arch/registers.py
puc16/ppci/arch/runtime.py
puc16/ppci/arch/stack.py
puc16/ppci/arch/target_list.py
puc16/ppci/arch/token.py
puc16/ppci/arch/puc16/__init__.py
puc16/ppci/arch/puc16/arch.py
puc16/ppci/arch/puc16/instructions.py
puc16/ppci/arch/puc16/registers.py
puc16/ppci/binutils/__init__.py
puc16/ppci/binutils/archive.py
puc16/ppci/binutils/assembler.py
puc16/ppci/binutils/debuginfo.py
puc16/ppci/binutils/disasm.py
puc16/ppci/binutils/layout.py
puc16/ppci/binutils/linker.py
puc16/ppci/binutils/objectfile.py
puc16/ppci/binutils/outstream.py
puc16/ppci/binutils/dbg/__init__.py
puc16/ppci/binutils/dbg/cli.py
puc16/ppci/binutils/dbg/debug_driver.py
puc16/ppci/binutils/dbg/debugger.py
puc16/ppci/binutils/dbg/dummy_driver.py
puc16/ppci/binutils/dbg/event.py
puc16/ppci/binutils/dbg/linux64debugdriver.py
puc16/ppci/binutils/dbg/ptcli.py
puc16/ppci/binutils/dbg/gdb/__init__.py
puc16/ppci/binutils/dbg/gdb/client.py
puc16/ppci/binutils/dbg/gdb/rsp.py
puc16/ppci/binutils/dbg/gdb/transport.py
puc16/ppci/cil/__init__.py
puc16/ppci/cil/io.py
puc16/ppci/codegen/__init__.py
puc16/ppci/codegen/burg.grammar
puc16/ppci/codegen/burg.py
puc16/ppci/codegen/codegen.py
puc16/ppci/codegen/dagsplit.py
puc16/ppci/codegen/flowgraph.py
puc16/ppci/codegen/instructionscheduler.py
puc16/ppci/codegen/instructionselector.py
puc16/ppci/codegen/interferencegraph.py
puc16/ppci/codegen/irdag.py
puc16-0.1.0.dist-info/LICENSE
puc16-0.1.0.dist-info/METADATA
puc16-0.1.0.dist-info/WHEEL
puc16-0.1.0.dist-info/entry_points.txt
puc16-0.1.0.dist-info/top_level.txt
puc16-0.1.0.dist-info/RECORD
