Metadata-Version: 2.1
Name: puc16
Version: 0.1.0
Summary: Assembler and C compiler for the PUC16 processor
Home-page: http://github.com/wcaarls/puc16
Author: Wouter Caarls
Author-email: wouter@puc-rio.br
License: GNU GPLv3+
Keywords: assembler compiler educational risc processor
Classifier: Development Status :: 4 - Beta
Classifier: Environment :: Console
Classifier: License :: OSI Approved :: GNU General Public License v3 or later (GPLv3+)
Classifier: Programming Language :: Python :: 3
Classifier: Topic :: Education
Classifier: Topic :: Software Development :: Assemblers
Classifier: Topic :: Software Development :: Compilers
License-File: LICENSE
